setup.py
xcy_Zscore/__init__.py
xcy_Zscore/xcy_Zscore.py
xcy_Zscore.egg-info/PKG-INFO
xcy_Zscore.egg-info/SOURCES.txt
xcy_Zscore.egg-info/dependency_links.txt
xcy_Zscore.egg-info/top_level.txt