Metadata-Version: 1.0
Name: xcy-Zscore
Version: 0.0.3
Summary: A small tool of Zscore based on numpy
Home-page: https://github.com/ChuanyuXue/mysmod/blob/master/zscore.py
Author: ChuanyuXue
Author-email: cs_xcy@126.com
License: UNKNOWN
Platform: UNKNOWN
